MANIFEST.in
README.rst
setup.py
docs/HISTORY.txt
docs/LICENSE.GPL
docs/LICENSE.txt
ftw/__init__.py
ftw.poodle.egg-info/PKG-INFO
ftw.poodle.egg-info/SOURCES.txt
ftw.poodle.egg-info/dependency_links.txt
ftw.poodle.egg-info/entry_points.txt
ftw.poodle.egg-info/namespace_packages.txt
ftw.poodle.egg-info/not-zip-safe
ftw.poodle.egg-info/requires.txt
ftw.poodle.egg-info/top_level.txt
ftw/poodle/__init__.py
ftw/poodle/adapters.py
ftw/poodle/config.py
ftw/poodle/configure.zcml
ftw/poodle/eventhandlers.py
ftw/poodle/interfaces.py
ftw/poodle/lawgiver.zcml
ftw/poodle/poodle_notification.pt
ftw/poodle/poodle_votes.py
ftw/poodle/skins.zcml
ftw/poodle/testing.py
ftw/poodle/tests.zcml
ftw/poodle/vocabularies.py
ftw/poodle/browser/__init__.py
ftw/poodle/browser/configure.zcml
ftw/poodle/browser/poodle.py
ftw/poodle/browser/poodletable.py
ftw/poodle/browser/submit_data.py
ftw/poodle/browser/templates/poodle.pt
ftw/poodle/browser/templates/poodletable.pt
ftw/poodle/browser/templates/voted.pt
ftw/poodle/content/__init__.py
ftw/poodle/content/configure.zcml
ftw/poodle/content/poodle.py
ftw/poodle/locales/ftw.poodle-manual.pot
ftw/poodle/locales/ftw.poodle.pot
ftw/poodle/locales/plone.pot
ftw/poodle/locales/de/LC_MESSAGES/ftw.poodle.po
ftw/poodle/locales/de/LC_MESSAGES/plone.po
ftw/poodle/locales/fr/LC_MESSAGES/ftw.poodle.po
ftw/poodle/locales/fr/LC_MESSAGES/plone.po
ftw/poodle/locales/it/LC_MESSAGES/ftw.poodle.po
ftw/poodle/locales/it/LC_MESSAGES/plone.po
ftw/poodle/profiles/default/cssregistry.xml
ftw/poodle/profiles/default/factorytool.xml
ftw/poodle/profiles/default/metadata.xml
ftw/poodle/profiles/default/rolemap.xml
ftw/poodle/profiles/default/skins.xml
ftw/poodle/profiles/default/types.xml
ftw/poodle/profiles/default/workflows.xml
ftw/poodle/profiles/default/types/Poodle.xml
ftw/poodle/profiles/default/workflows/poodle_workflow/definition.xml
ftw/poodle/skins/ftw.poodle/poodle.css.dtml
ftw/poodle/skins/ftw.poodle/poodle.jpg
ftw/poodle/tests/__init__.py
ftw/poodle/tests/builders.py
ftw/poodle/tests/doc_tests.py
ftw/poodle/tests/test_notification.py
ftw/poodle/tests/test_stealth_voting.py
ftw/poodle/tests/test_submit.py
ftw/poodle/tests/test_votes.py
ftw/poodle/upgrades/__init__.py
ftw/poodle/upgrades/configure.zcml
