Metadata-Version: 1.1
Name: ftw.poodle
Version: 1.6.0
Summary: A product to make polls to find out when to have a meeting
Home-page: https://github.com/4teamwork/ftw.poodle
Author: Mathias Leimgruber
Author-email: mailto:info@4teamwork.ch
License: GPL2
Keywords: ftw poodle doodle events plone
Platform: UNKNOWN
Classifier: Framework :: Plone
Classifier: Framework :: Plone :: 4.1
Classifier: Framework :: Plone :: 4.2
Classifier: Framework :: Plone :: 4.3
Classifier: Programming Language :: Python
Classifier: Topic :: Software Development :: Libraries :: Python Modules
